CHANGELOG.txt
LICENCE.txt
MANIFEST.in
README.txt
setup.py
CMetasploit/__init__.py
CMetasploit.egg-info/PKG-INFO
CMetasploit.egg-info/SOURCES.txt
CMetasploit.egg-info/dependency_links.txt
CMetasploit.egg-info/top_level.txt