Metadata-Version: 2.1
Name: CMetasploit
Version: 0.0.2
Summary: Welcome
Home-page: 
Author: Ankit
Author-email: codexstudiosltd@gmail.com
License: MIT
Keywords: CMetasploit
Classifier: Development Status :: 5 - Production/Stable
Classifier: Intended Audience :: Education
Classifier: Operating System :: Microsoft
Classifier: Operating System :: Microsoft :: Windows :: Windows 10
Classifier: License :: OSI Approved :: MIT License
Classifier: Programming Language :: Python :: 3
License-File: LICENCE.txt
